setup.py
asklet/__init__.py
asklet/admin.py
asklet/classifier.py
asklet/constants.py
asklet/models.py
asklet/settings.py
asklet/utils.py
asklet.egg-info/PKG-INFO
asklet.egg-info/SOURCES.txt
asklet.egg-info/dependency_links.txt
asklet.egg-info/not-zip-safe
asklet.egg-info/requires.txt
asklet.egg-info/top_level.txt
asklet/backends/__init__.py
asklet/backends/base.py
asklet/backends/sql.py
asklet/management/__init__.py
asklet/management/commands/__init__.py
asklet/management/commands/asklet_play.py
asklet/management/commands/asklet_rank.py
asklet/management/commands/asklet_simulate.py
asklet/migrations/0001_initial.py
asklet/migrations/__init__.py
asklet/tests/__init__.py
asklet/tests/models.py
asklet/tests/settings.py
asklet/tests/settings_local.py
asklet/tests/tests.py
asklet/tests/urls.py