Metadata-Version: 1.1
Name: asklet
Version: 0.0.2
Summary: A learning algorithm for the 20 questions game.
Home-page: https://github.com/chrisspen/asklet
Author: Chris Spencer
Author-email: chrisspen@gmail.com
License: LGPL
Platform: UNKNOWN
Classifier: Intended Audience :: Developers
Classifier: License :: OSI Approved :: GNU Lesser General Public License v3 (LGPLv3)
Classifier: Operating System :: OS Independent
Classifier: Programming Language :: Python
Classifier: Programming Language :: Python :: 2.7
Classifier: Programming Language :: Python :: 3.2
Classifier: Framework :: Django
Classifier: Topic :: Scientific/Engineering :: Artificial Intelligence
